gillespy2/__init__.py
gillespy2/__version__.py
gillespy2/core/__init__.py
gillespy2/core/assignmentrule.py
gillespy2/core/cleanup.py
gillespy2/core/events.py
gillespy2/core/functiondefinition.py
gillespy2/core/gillespyError.py
gillespy2/core/gillespySolver.py
gillespy2/core/jsonify.py
gillespy2/core/liveGraphing.py
gillespy2/core/model.py
gillespy2/core/parameter.py
gillespy2/core/raterule.py
gillespy2/core/reaction.py
gillespy2/core/results.py
gillespy2/core/sortableobject.py
gillespy2/core/species.py
gillespy2/core/timespan.py
gillespy2/sbml/SBMLexport.py
gillespy2/sbml/SBMLimport.py
gillespy2/sbml/__init__.py
gillespy2/solvers/__init__.py
gillespy2/solvers/cpp/__init__.py
gillespy2/solvers/cpp/c_decoder.py
gillespy2/solvers/cpp/c_solver.py
gillespy2/solvers/cpp/ode_c_solver.py
gillespy2/solvers/cpp/ssa_c_solver.py
gillespy2/solvers/cpp/tau_hybrid_c_solver.py
gillespy2/solvers/cpp/tau_leaping_c_solver.py
gillespy2/solvers/cpp/build/SConstruct
gillespy2/solvers/cpp/build/__init__.py
gillespy2/solvers/cpp/build/build_engine.py
gillespy2/solvers/cpp/build/expression.py
gillespy2/solvers/cpp/build/make.py
gillespy2/solvers/cpp/build/template_gen.py
gillespy2/solvers/cpp/c_base/SConscript
gillespy2/solvers/cpp/c_base/arg_parser.cpp
gillespy2/solvers/cpp/c_base/arg_parser.h
gillespy2/solvers/cpp/c_base/model.cpp
gillespy2/solvers/cpp/c_base/model.h
gillespy2/solvers/cpp/c_base/Sundials/LICENSE
gillespy2/solvers/cpp/c_base/Sundials/NOTICE
gillespy2/solvers/cpp/c_base/Sundials/README.md
gillespy2/solvers/cpp/c_base/Sundials/SConscript
gillespy2/solvers/cpp/c_base/Sundials/include/cvode.h
gillespy2/solvers/cpp/c_base/Sundials/include/cvode_ls.h
gillespy2/solvers/cpp/c_base/Sundials/include/cvode_proj.h
gillespy2/solvers/cpp/c_base/Sundials/include/cvode_spils.h
gillespy2/solvers/cpp/c_base/Sundials/include/nvector_serial.h
gillespy2/solvers/cpp/c_base/Sundials/include/sundials_band.h
gillespy2/solvers/cpp/c_base/Sundials/include/sundials_config.h
gillespy2-1.8.3.dist-info/LICENSE
gillespy2-1.8.3.dist-info/METADATA
gillespy2-1.8.3.dist-info/WHEEL
gillespy2-1.8.3.dist-info/top_level.txt
gillespy2-1.8.3.dist-info/RECORD
