Metadata-Version: 2.1
Name: gillespy2
Version: 1.8.3
Summary: Python interface for Gillespie-style biochemical simulations
Home-page: https://github.com/StochSS/GillesPy2
Author: See AUTHORS
Author-email: briandrawert@gmail.com
Maintainer: See AUTHORS
Maintainer-email: briandrawert@gmail.com
License: GPL
Download-URL: https://pypi.org/project/gillespy2/#files
Project-URL: Tracker, https://github.com/StochSS/GillesPy2/issues
Project-URL: Source, https://github.com/StochSS/GillesPy2
Keywords: biochemical simulation,Gillespie algorithm,stochastic simulation,biology
Platform: UNKNOWN
Classifier: Development Status :: 5 - Production/Stable
Classifier: License :: OSI Approved :: GNU General Public License v3 (GPLv3)
Classifier: Operating System :: OS Independent
Classifier: Programming Language :: Python :: 3
Classifier: Topic :: Scientific/Engineering
Classifier: Topic :: Scientific/Engineering :: Chemistry
Classifier: Topic :: Scientific/Engineering :: Mathematics
Classifier: Topic :: Scientific/Engineering :: Medical Science Apps.
Classifier: Intended Audience :: Science/Research
License-File: LICENSE
Requires-Dist: matplotlib (>=3.0.3)
Requires-Dist: plotly (>=4.1.0)
Requires-Dist: scipy (>=1.3.1)
Requires-Dist: setuptools (>=41.0.1)
Requires-Dist: numpy (>=1.18.5)
Requires-Dist: scons (>=4.4.0)
